powershap/__init__.py
powershap/powershap.py
powershap/utils.py
powershap/shap_wrappers/__init__.py
powershap/shap_wrappers/shap_explainer.py
powershap/shap_wrappers/shap_explainer_factory.py
powershap-0.1.0.1.dist-info/METADATA
powershap-0.1.0.1.dist-info/WHEEL
powershap-0.1.0.1.dist-info/licenses/LICENSE
powershap-0.1.0.1.dist-info/RECORD
