Metadata-Version: 2.4
Name: powershap
Version: 0.1.0.1
Summary: Feature selection using statistical significance of shap values
Project-URL: Repository, https://github.com/predict-idlab/powershap
Author: Jarne Verhaeghe, Jeroen Van Der Donckt
License-Expression: MIT
License-File: LICENSE
Keywords: data-science,feature selection,machine learning,shap
Classifier: Development Status :: 5 - Production/Stable
Classifier: Intended Audience :: Developers
Classifier: License :: OSI Approved :: MIT License
Classifier: Operating System :: MacOS :: MacOS X
Classifier: Operating System :: Microsoft :: Windows
Classifier: Operating System :: POSIX :: Linux
Classifier: Programming Language :: Python
Classifier: Programming Language :: Python :: 3
Classifier: Programming Language :: Python :: 3.9
Classifier: Programming Language :: Python :: 3.10
Classifier: Programming Language :: Python :: 3.11
Classifier: Programming Language :: Python :: 3.12
Classifier: Programming Language :: Python :: 3.13
Requires-Python: <=3.13,>=3.9
Requires-Dist: catboost>=1.0.5
Requires-Dist: pandas>=1.3
Requires-Dist: scikit-learn>=1.6
Requires-Dist: shap<0.46,>=0.45.0
Requires-Dist: statsmodels>=0.14.0
